ssu_timetable/__init__.py
ssu_timetable/browser.py
ssu_timetable/config.py
ssu_timetable/event_generator.py
ssu_timetable/parser.py
ssu_timetable/sanitizer.py
ssu_timetable-0.0.1.dist-info/LICENSE
ssu_timetable-0.0.1.dist-info/METADATA
ssu_timetable-0.0.1.dist-info/WHEEL
ssu_timetable-0.0.1.dist-info/top_level.txt
ssu_timetable-0.0.1.dist-info/RECORD
