Metadata-Version: 2.1
Name: ssu-timetable
Version: 0.0.1
Summary: SSU subject parser
Home-page: https://github.com/rubycho/ssu-timetable
Author: rubycho
Author-email: rubycho@outlook.kr
License: UNKNOWN
Platform: UNKNOWN
Classifier: Programming Language :: Python :: 3
Classifier: License :: OSI Approved :: MIT License
Classifier: Operating System :: OS Independent
Requires-Python: >=3.6
Requires-Dist: lxml
Requires-Dist: bs4
Requires-Dist: requests
